odoo/addons/ddmrp_product_replace/README.rst
odoo/addons/ddmrp_product_replace/__init__.py
odoo/addons/ddmrp_product_replace/__manifest__.py
odoo/addons/ddmrp_product_replace/i18n/ddmrp_product_replace.pot
odoo/addons/ddmrp_product_replace/i18n/es.po
odoo/addons/ddmrp_product_replace/i18n/it.po
odoo/addons/ddmrp_product_replace/i18n/pt_BR.po
odoo/addons/ddmrp_product_replace/models/__init__.py
odoo/addons/ddmrp_product_replace/models/stock_buffer.py
odoo/addons/ddmrp_product_replace/models/stock_move.py
odoo/addons/ddmrp_product_replace/readme/CONTRIBUTORS.md
odoo/addons/ddmrp_product_replace/readme/CREDITS.md
odoo/addons/ddmrp_product_replace/readme/DESCRIPTION.md
odoo/addons/ddmrp_product_replace/readme/ROADMAP.md
odoo/addons/ddmrp_product_replace/readme/USAGE.md
odoo/addons/ddmrp_product_replace/security/ir.model.access.csv
odoo/addons/ddmrp_product_replace/static/description/icon.png
odoo/addons/ddmrp_product_replace/static/description/index.html
odoo/addons/ddmrp_product_replace/tests/__init__.py
odoo/addons/ddmrp_product_replace/tests/test_product_replace.py
odoo/addons/ddmrp_product_replace/views/stock_buffer_view.xml
odoo/addons/ddmrp_product_replace/wizards/__init__.py
odoo/addons/ddmrp_product_replace/wizards/ddmrp_product_replace.py
odoo/addons/ddmrp_product_replace/wizards/ddmrp_product_replace_view.xml
odoo/addons/ddmrp_product_replace/wizards/make_procurement_buffer.py
odoo/addons/ddmrp_product_replace/wizards/make_procurement_buffer_view.xml
odoo_addon_ddmrp_product_replace-18.0.1.0.0.3.dist-info/METADATA
odoo_addon_ddmrp_product_replace-18.0.1.0.0.3.dist-info/WHEEL
odoo_addon_ddmrp_product_replace-18.0.1.0.0.3.dist-info/top_level.txt
odoo_addon_ddmrp_product_replace-18.0.1.0.0.3.dist-info/RECORD
